[
    {
        "pickupBgAssetBundleName": "", 
        "positionX": 0, 
        "positionY": 0, 
        "createdTime": 1582038000, 
        "objectId": 107, 
        "pickupBgResourceName": "", 
        "priority": 1, 
        "gachaPickupMstId": 4, 
        "startTime": 1577804400, 
        "gachaSeriesMstId": 2, 
        "endTime": 1917824400, 
        "pickupSkillType": 1, 
        "objectType": 1
    }, 
    {
        "pickupBgAssetBundleName": "", 
        "positionX": 0, 
        "positionY": 0, 
        "createdTime": 1582038000, 
        "objectId": 41, 
        "pickupBgResourceName": "", 
        "priority": 2, 
        "gachaPickupMstId": 5, 
        "startTime": 1577804400, 
        "gachaSeriesMstId": 2, 
        "endTime": 1917824400, 
        "pickupSkillType": 1, 
        "objectType": 1
    }, 
    {
        "pickupBgAssetBundleName": "", 
        "positionX": 0, 
        "positionY": 0, 
        "createdTime": 1582038000, 
        "objectId": 205, 
        "pickupBgResourceName": "", 
        "priority": 3, 
        "gachaPickupMstId": 6, 
        "startTime": 1577804400, 
        "gachaSeriesMstId": 2, 
        "endTime": 1917824400, 
        "pickupSkillType": 1, 
        "objectType": 1
    }, 
    {
        "pickupBgAssetBundleName": "", 
        "positionX": 0, 
        "positionY": 0, 
        "createdTime": 1467266400, 
        "objectId": 1564, 
        "pickupBgResourceName": "", 
        "priority": 1, 
        "gachaPickupMstId": 74, 
        "startTime": 1619503200, 
        "gachaSeriesMstId": 26, 
        "endTime": 1619675999, 
        "pickupSkillType": 1, 
        "objectType": 1
    }, 
    {
        "pickupBgAssetBundleName": "", 
        "positionX": 0, 
        "positionY": 0, 
        "createdTime": 1467266400, 
        "objectId": 41, 
        "pickupBgResourceName": "", 
        "priority": 2, 
        "gachaPickupMstId": 75, 
        "startTime": 1619503200, 
        "gachaSeriesMstId": 26, 
        "endTime": 1619675999, 
        "pickupSkillType": 1, 
        "objectType": 1
    }, 
    {
        "pickupBgAssetBundleName": "", 
        "positionX": -80, 
        "positionY": 90, 
        "createdTime": 1467266400, 
        "objectId": 1049, 
        "pickupBgResourceName": "", 
        "priority": 3, 
        "gachaPickupMstId": 76, 
        "startTime": 1619503200, 
        "gachaSeriesMstId": 26, 
        "endTime": 1619675999, 
        "pickupSkillType": 1, 
        "objectType": 1
    }, 
    {
        "pickupBgAssetBundleName": "", 
        "positionX": 0, 
        "positionY": 0, 
        "createdTime": 1467266400, 
        "objectId": 2023, 
        "pickupBgResourceName": "", 
        "priority": 1, 
        "gachaPickupMstId": 77, 
        "startTime": 1619676000, 
        "gachaSeriesMstId": 27, 
        "endTime": 1619848799, 
        "pickupSkillType": 1, 
        "objectType": 1
    }, 
    {
        "pickupBgAssetBundleName": "", 
        "positionX": 0, 
        "positionY": 100, 
        "createdTime": 1467266400, 
        "objectId": 787, 
        "pickupBgResourceName": "", 
        "priority": 2, 
        "gachaPickupMstId": 78, 
        "startTime": 1619676000, 
        "gachaSeriesMstId": 27, 
        "endTime": 1619848799, 
        "pickupSkillType": 1, 
        "objectType": 1
    }, 
    {
        "pickupBgAssetBundleName": "", 
        "positionX": 0, 
        "positionY": 0, 
        "createdTime": 1467266400, 
        "objectId": 107, 
        "pickupBgResourceName": "", 
        "priority": 3, 
        "gachaPickupMstId": 79, 
        "startTime": 1619676000, 
        "gachaSeriesMstId": 27, 
        "endTime": 1619848799, 
        "pickupSkillType": 1, 
        "objectType": 1
    }, 
    {
        "pickupBgAssetBundleName": "", 
        "positionX": 0, 
        "positionY": 0, 
        "createdTime": 1467266400, 
        "objectId": 2110, 
        "pickupBgResourceName": "", 
        "priority": 1, 
        "gachaPickupMstId": 80, 
        "startTime": 1619848800, 
        "gachaSeriesMstId": 28, 
        "endTime": 1620021599, 
        "pickupSkillType": 1, 
        "objectType": 1
    }, 
    {
        "pickupBgAssetBundleName": "", 
        "positionX": 0, 
        "positionY": 0, 
        "createdTime": 1467266400, 
        "objectId": 1616, 
        "pickupBgResourceName": "", 
        "priority": 2, 
        "gachaPickupMstId": 81, 
        "startTime": 1619848800, 
        "gachaSeriesMstId": 28, 
        "endTime": 1620021599, 
        "pickupSkillType": 1, 
        "objectType": 1
    }, 
    {
        "pickupBgAssetBundleName": "", 
        "positionX": 0, 
        "positionY": 0, 
        "createdTime": 1467266400, 
        "objectId": 1905, 
        "pickupBgResourceName": "", 
        "priority": 3, 
        "gachaPickupMstId": 82, 
        "startTime": 1619848800, 
        "gachaSeriesMstId": 28, 
        "endTime": 1620021599, 
        "pickupSkillType": 1, 
        "objectType": 1
    }, 
    {
        "pickupBgAssetBundleName": "", 
        "positionX": 0, 
        "positionY": 0, 
        "createdTime": 1467266400, 
        "objectId": 993, 
        "pickupBgResourceName": "", 
        "priority": 1, 
        "gachaPickupMstId": 642, 
        "startTime": 1617084000, 
        "gachaSeriesMstId": 213, 
        "endTime": 1619762399, 
        "pickupSkillType": 1, 
        "objectType": 1
    }, 
    {
        "pickupBgAssetBundleName": "", 
        "positionX": 0, 
        "positionY": 0, 
        "createdTime": 1467266400, 
        "objectId": 775, 
        "pickupBgResourceName": "", 
        "priority": 2, 
        "gachaPickupMstId": 643, 
        "startTime": 1617084000, 
        "gachaSeriesMstId": 213, 
        "endTime": 1619762399, 
        "pickupSkillType": 1, 
        "objectType": 1
    }, 
    {
        "pickupBgAssetBundleName": "", 
        "positionX": 0, 
        "positionY": 0, 
        "createdTime": 1467266400, 
        "objectId": 743, 
        "pickupBgResourceName": "", 
        "priority": 3, 
        "gachaPickupMstId": 644, 
        "startTime": 1617084000, 
        "gachaSeriesMstId": 213, 
        "endTime": 1619762399, 
        "pickupSkillType": 1, 
        "objectType": 2
    }, 
    {
        "pickupBgAssetBundleName": "", 
        "positionX": 0, 
        "positionY": 0, 
        "createdTime": 1467266400, 
        "objectId": 2356, 
        "pickupBgResourceName": "", 
        "priority": 1, 
        "gachaPickupMstId": 672, 
        "startTime": 1618898400, 
        "gachaSeriesMstId": 222, 
        "endTime": 1620107999, 
        "pickupSkillType": 1, 
        "objectType": 1
    }, 
    {
        "pickupBgAssetBundleName": "", 
        "positionX": 0, 
        "positionY": 0, 
        "createdTime": 1467266400, 
        "objectId": 2360, 
        "pickupBgResourceName": "", 
        "priority": 2, 
        "gachaPickupMstId": 673, 
        "startTime": 1618898400, 
        "gachaSeriesMstId": 222, 
        "endTime": 1620107999, 
        "pickupSkillType": 1, 
        "objectType": 1
    }, 
    {
        "pickupBgAssetBundleName": "", 
        "positionX": 0, 
        "positionY": 0, 
        "createdTime": 1467266400, 
        "objectId": 2362, 
        "pickupBgResourceName": "", 
        "priority": 4, 
        "gachaPickupMstId": 674, 
        "startTime": 1618898400, 
        "gachaSeriesMstId": 222, 
        "endTime": 1620107999, 
        "pickupSkillType": 1, 
        "objectType": 1
    }, 
    {
        "pickupBgAssetBundleName": "", 
        "positionX": 0, 
        "positionY": 0, 
        "createdTime": 1467266400, 
        "objectId": 107, 
        "pickupBgResourceName": "", 
        "priority": 1, 
        "gachaPickupMstId": 692, 
        "startTime": 1600322400, 
        "gachaSeriesMstId": 9000, 
        "endTime": 1924959599, 
        "pickupSkillType": 1, 
        "objectType": 1
    }, 
    {
        "pickupBgAssetBundleName": "", 
        "positionX": 0, 
        "positionY": 0, 
        "createdTime": 1467266400, 
        "objectId": 41, 
        "pickupBgResourceName": "", 
        "priority": 2, 
        "gachaPickupMstId": 693, 
        "startTime": 1600322400, 
        "gachaSeriesMstId": 9000, 
        "endTime": 1924959599, 
        "pickupSkillType": 1, 
        "objectType": 1
    }, 
    {
        "pickupBgAssetBundleName": "", 
        "positionX": 0, 
        "positionY": 0, 
        "createdTime": 1467266400, 
        "objectId": 103, 
        "pickupBgResourceName": "", 
        "priority": 3, 
        "gachaPickupMstId": 694, 
        "startTime": 1600322400, 
        "gachaSeriesMstId": 9000, 
        "endTime": 1924959599, 
        "pickupSkillType": 1, 
        "objectType": 1
    }, 
    {
        "pickupBgAssetBundleName": "", 
        "positionX": 0, 
        "positionY": 0, 
        "createdTime": 1467266400, 
        "objectId": 2418, 
        "pickupBgResourceName": "", 
        "priority": 1, 
        "gachaPickupMstId": 701, 
        "startTime": 1619157600, 
        "gachaSeriesMstId": 228, 
        "endTime": 1620367199, 
        "pickupSkillType": 1, 
        "objectType": 1
    }, 
    {
        "pickupBgAssetBundleName": "", 
        "positionX": 0, 
        "positionY": 0, 
        "createdTime": 1467266400, 
        "objectId": 2426, 
        "pickupBgResourceName": "", 
        "priority": 2, 
        "gachaPickupMstId": 702, 
        "startTime": 1619157600, 
        "gachaSeriesMstId": 228, 
        "endTime": 1620367199, 
        "pickupSkillType": 1, 
        "objectType": 2
    }, 
    {
        "pickupBgAssetBundleName": "", 
        "positionX": 0, 
        "positionY": 0, 
        "createdTime": 1467266400, 
        "objectId": 2386, 
        "pickupBgResourceName": "", 
        "priority": 3, 
        "gachaPickupMstId": 703, 
        "startTime": 1619157600, 
        "gachaSeriesMstId": 228, 
        "endTime": 1620367199, 
        "pickupSkillType": 1, 
        "objectType": 1
    }, 
    {
        "pickupBgAssetBundleName": "", 
        "positionX": 0, 
        "positionY": 0, 
        "createdTime": 1467266400, 
        "objectId": 4691, 
        "pickupBgResourceName": "", 
        "priority": 1, 
        "gachaPickupMstId": 5833, 
        "startTime": 1618552800, 
        "gachaSeriesMstId": 100610, 
        "endTime": 1619762399, 
        "pickupSkillType": 1, 
        "objectType": 1
    }, 
    {
        "pickupBgAssetBundleName": "", 
        "positionX": 0, 
        "positionY": 0, 
        "createdTime": 1467266400, 
        "objectId": 4741, 
        "pickupBgResourceName": "", 
        "priority": 2, 
        "gachaPickupMstId": 5834, 
        "startTime": 1618552800, 
        "gachaSeriesMstId": 100610, 
        "endTime": 1619762399, 
        "pickupSkillType": 1, 
        "objectType": 1
    }, 
    {
        "pickupBgAssetBundleName": "", 
        "positionX": 0, 
        "positionY": 0, 
        "createdTime": 1467266400, 
        "objectId": 4747, 
        "pickupBgResourceName": "", 
        "priority": 3, 
        "gachaPickupMstId": 5835, 
        "startTime": 1618552800, 
        "gachaSeriesMstId": 100610, 
        "endTime": 1619762399, 
        "pickupSkillType": 1, 
        "objectType": 1
    }, 
    {
        "pickupBgAssetBundleName": "", 
        "positionX": 0, 
        "positionY": 0, 
        "createdTime": 1467266400, 
        "objectId": 4749, 
        "pickupBgResourceName": "", 
        "priority": 4, 
        "gachaPickupMstId": 5836, 
        "startTime": 1618552800, 
        "gachaSeriesMstId": 100610, 
        "endTime": 1619762399, 
        "pickupSkillType": 1, 
        "objectType": 1
    }, 
    {
        "pickupBgAssetBundleName": "", 
        "positionX": 0, 
        "positionY": 0, 
        "createdTime": 1467266400, 
        "objectId": 4693, 
        "pickupBgResourceName": "", 
        "priority": 2, 
        "gachaPickupMstId": 5837, 
        "startTime": 1618552800, 
        "gachaSeriesMstId": 100620, 
        "endTime": 1619762399, 
        "pickupSkillType": 1, 
        "objectType": 1
    }, 
    {
        "pickupBgAssetBundleName": "", 
        "positionX": 0, 
        "positionY": 0, 
        "createdTime": 1467266400, 
        "objectId": 4695, 
        "pickupBgResourceName": "", 
        "priority": 1, 
        "gachaPickupMstId": 5838, 
        "startTime": 1618552800, 
        "gachaSeriesMstId": 100620, 
        "endTime": 1619762399, 
        "pickupSkillType": 1, 
        "objectType": 1
    }, 
    {
        "pickupBgAssetBundleName": "", 
        "positionX": 0, 
        "positionY": 0, 
        "createdTime": 1467266400, 
        "objectId": 4743, 
        "pickupBgResourceName": "", 
        "priority": 3, 
        "gachaPickupMstId": 5839, 
        "startTime": 1618552800, 
        "gachaSeriesMstId": 100620, 
        "endTime": 1619762399, 
        "pickupSkillType": 1, 
        "objectType": 1
    }, 
    {
        "pickupBgAssetBundleName": "", 
        "positionX": 0, 
        "positionY": 0, 
        "createdTime": 1467266400, 
        "objectId": 4745, 
        "pickupBgResourceName": "", 
        "priority": 4, 
        "gachaPickupMstId": 5840, 
        "startTime": 1618552800, 
        "gachaSeriesMstId": 100620, 
        "endTime": 1619762399, 
        "pickupSkillType": 1, 
        "objectType": 1
    }, 
    {
        "pickupBgAssetBundleName": "", 
        "positionX": 0, 
        "positionY": 0, 
        "createdTime": 1467266400, 
        "objectId": 4691, 
        "pickupBgResourceName": "", 
        "priority": 1, 
        "gachaPickupMstId": 5841, 
        "startTime": 1618552800, 
        "gachaSeriesMstId": 825, 
        "endTime": 1620399599, 
        "pickupSkillType": 1, 
        "objectType": 1
    }, 
    {
        "pickupBgAssetBundleName": "", 
        "positionX": 0, 
        "positionY": 0, 
        "createdTime": 1467266400, 
        "objectId": 4741, 
        "pickupBgResourceName": "", 
        "priority": 2, 
        "gachaPickupMstId": 5842, 
        "startTime": 1618552800, 
        "gachaSeriesMstId": 825, 
        "endTime": 1620399599, 
        "pickupSkillType": 1, 
        "objectType": 1
    }, 
    {
        "pickupBgAssetBundleName": "", 
        "positionX": 0, 
        "positionY": 0, 
        "createdTime": 1467266400, 
        "objectId": 4693, 
        "pickupBgResourceName": "", 
        "priority": 2, 
        "gachaPickupMstId": 5843, 
        "startTime": 1618552800, 
        "gachaSeriesMstId": 826, 
        "endTime": 1620399599, 
        "pickupSkillType": 1, 
        "objectType": 1
    }, 
    {
        "pickupBgAssetBundleName": "", 
        "positionX": 0, 
        "positionY": 0, 
        "createdTime": 1467266400, 
        "objectId": 4695, 
        "pickupBgResourceName": "", 
        "priority": 1, 
        "gachaPickupMstId": 5844, 
        "startTime": 1618552800, 
        "gachaSeriesMstId": 826, 
        "endTime": 1620399599, 
        "pickupSkillType": 1, 
        "objectType": 1
    }, 
    {
        "pickupBgAssetBundleName": "", 
        "positionX": 0, 
        "positionY": 0, 
        "createdTime": 1467266400, 
        "objectId": 205, 
        "pickupBgResourceName": "", 
        "priority": 4, 
        "gachaPickupMstId": 900001, 
        "startTime": 1600322400, 
        "gachaSeriesMstId": 9000, 
        "endTime": 1924959599, 
        "pickupSkillType": 1, 
        "objectType": 1
    }, 
    {
        "pickupBgAssetBundleName": "", 
        "positionX": 0, 
        "positionY": 0, 
        "createdTime": 1467266400, 
        "objectId": 207, 
        "pickupBgResourceName": "", 
        "priority": 5, 
        "gachaPickupMstId": 900002, 
        "startTime": 1600322400, 
        "gachaSeriesMstId": 9000, 
        "endTime": 1924959599, 
        "pickupSkillType": 1, 
        "objectType": 1
    }, 
    {
        "pickupBgAssetBundleName": "", 
        "positionX": 0, 
        "positionY": 0, 
        "createdTime": 1602774000, 
        "objectId": 900002, 
        "pickupBgResourceName": "", 
        "priority": 5, 
        "gachaPickupMstId": 900013, 
        "startTime": 1605765600, 
        "gachaSeriesMstId": 900003, 
        "endTime": 1924959599, 
        "pickupSkillType": 1, 
        "objectType": 1
    }, 
    {
        "pickupBgAssetBundleName": "", 
        "positionX": 0, 
        "positionY": 0, 
        "createdTime": 1602774000, 
        "objectId": 900004, 
        "pickupBgResourceName": "", 
        "priority": 6, 
        "gachaPickupMstId": 900014, 
        "startTime": 1605765600, 
        "gachaSeriesMstId": 900003, 
        "endTime": 1924959599, 
        "pickupSkillType": 1, 
        "objectType": 1
    }, 
    {
        "pickupBgAssetBundleName": "", 
        "positionX": 0, 
        "positionY": 0, 
        "createdTime": 1602774000, 
        "objectId": 900008, 
        "pickupBgResourceName": "", 
        "priority": 7, 
        "gachaPickupMstId": 900016, 
        "startTime": 1605765600, 
        "gachaSeriesMstId": 900003, 
        "endTime": 1924959599, 
        "pickupSkillType": 1, 
        "objectType": 1
    }, 
    {
        "pickupBgAssetBundleName": "", 
        "positionX": 0, 
        "positionY": 0, 
        "createdTime": 1602774000, 
        "objectId": 900010, 
        "pickupBgResourceName": "", 
        "priority": 1, 
        "gachaPickupMstId": 900017, 
        "startTime": 1605765600, 
        "gachaSeriesMstId": 900003, 
        "endTime": 1924959599, 
        "pickupSkillType": 1, 
        "objectType": 1
    }, 
    {
        "pickupBgAssetBundleName": "", 
        "positionX": 0, 
        "positionY": 0, 
        "createdTime": 1602774000, 
        "objectId": 900012, 
        "pickupBgResourceName": "", 
        "priority": 2, 
        "gachaPickupMstId": 900018, 
        "startTime": 1605765600, 
        "gachaSeriesMstId": 900003, 
        "endTime": 1924959599, 
        "pickupSkillType": 1, 
        "objectType": 1
    }, 
    {
        "pickupBgAssetBundleName": "", 
        "positionX": 0, 
        "positionY": 0, 
        "createdTime": 1602774000, 
        "objectId": 900014, 
        "pickupBgResourceName": "", 
        "priority": 3, 
        "gachaPickupMstId": 900019, 
        "startTime": 1605765600, 
        "gachaSeriesMstId": 900003, 
        "endTime": 1924959599, 
        "pickupSkillType": 1, 
        "objectType": 1
    }, 
    {
        "pickupBgAssetBundleName": "", 
        "positionX": 0, 
        "positionY": 0, 
        "createdTime": 1602774000, 
        "objectId": 900016, 
        "pickupBgResourceName": "", 
        "priority": 4, 
        "gachaPickupMstId": 900020, 
        "startTime": 1605765600, 
        "gachaSeriesMstId": 900003, 
        "endTime": 1924959599, 
        "pickupSkillType": 1, 
        "objectType": 1
    }, 
    {
        "pickupBgAssetBundleName": "", 
        "positionX": 0, 
        "positionY": 0, 
        "createdTime": 1611846000, 
        "objectId": 1011, 
        "pickupBgResourceName": "", 
        "priority": 1, 
        "gachaPickupMstId": 900085, 
        "startTime": 1618552800, 
        "gachaSeriesMstId": 900018, 
        "endTime": 1619762399, 
        "pickupSkillType": 1, 
        "objectType": 1
    }, 
    {
        "pickupBgAssetBundleName": "", 
        "positionX": 0, 
        "positionY": 0, 
        "createdTime": 1611846000, 
        "objectId": 2023, 
        "pickupBgResourceName": "", 
        "priority": 2, 
        "gachaPickupMstId": 900086, 
        "startTime": 1618552800, 
        "gachaSeriesMstId": 900018, 
        "endTime": 1619762399, 
        "pickupSkillType": 1, 
        "objectType": 1
    }, 
    {
        "pickupBgAssetBundleName": "", 
        "positionX": 0, 
        "positionY": 0, 
        "createdTime": 1611846000, 
        "objectId": 2110, 
        "pickupBgResourceName": "", 
        "priority": 3, 
        "gachaPickupMstId": 900087, 
        "startTime": 1618552800, 
        "gachaSeriesMstId": 900018, 
        "endTime": 1619762399, 
        "pickupSkillType": 1, 
        "objectType": 1
    }, 
    {
        "pickupBgAssetBundleName": "", 
        "positionX": 0, 
        "positionY": 0, 
        "createdTime": 1611846000, 
        "objectId": 1574, 
        "pickupBgResourceName": "", 
        "priority": 4, 
        "gachaPickupMstId": 900088, 
        "startTime": 1618552800, 
        "gachaSeriesMstId": 900018, 
        "endTime": 1619762399, 
        "pickupSkillType": 1, 
        "objectType": 1
    }, 
    {
        "pickupBgAssetBundleName": "", 
        "positionX": 0, 
        "positionY": 0, 
        "createdTime": 1467266400, 
        "objectId": 3196, 
        "pickupBgResourceName": "", 
        "priority": 3, 
        "gachaPickupMstId": 900089, 
        "startTime": 1618898400, 
        "gachaSeriesMstId": 222, 
        "endTime": 1620107999, 
        "pickupSkillType": 1, 
        "objectType": 1
    }
]
